compost/__init__.py
compost/dataset.py
compost/model.py
compost/saving_calculation.py
compost-0.2.8.dist-info/LICENSE
compost-0.2.8.dist-info/METADATA
compost-0.2.8.dist-info/WHEEL
compost-0.2.8.dist-info/top_level.txt
compost-0.2.8.dist-info/RECORD
