Metadata-Version: 2.1
Name: compost
Version: 0.2.8
Summary: Compost is an energy consumption modelling toolkit for inverse modelling of energy consumption using measured data
Home-page: https://github.com/ggstuart/compost
Author: Graeme Stuart
Author-email: gstuart@dmu.ac.uk
License: UNKNOWN
Keywords: energy consumption inverse modelling
Platform: UNKNOWN
Classifier: Development Status :: 3 - Alpha
Classifier: License :: OSI Approved :: GNU General Public License v3 (GPLv3)
Classifier: Programming Language :: Python
Classifier: Intended Audience :: Science/Research
Classifier: Topic :: Scientific/Engineering :: Information Analysis
